{
	"local_host": "0.0.0.0",
	"local_port": 30303,
	"listen": true,
	"remote_host": "",
	"remote_port": 30303,
	"use_seed": false,
	"rpc_host": "",
	"rpc_port": 30304,
	"serve_rpc": false,
	"fetch_port": 50505,
	"chain_id": "",
	"chain_name": "",
	"mining": false,
	"max_peers": 10,
	"client": "Thelonious(decerver)",
	"version": "0.7.0",
	"id": "",
	"key_session": "generous",
	"key_store": "file",
	"key_cursor": 0,
	"key_file": "",
	"adversary": 0,
	"use_checkpoint": false,
	"latest_checkpoint": "",
	"config_file": "config",
	"root_dir": "",
	"db_name": "database",
	"db_mem": false,
	"contract_path": "/home/zqa/go/src/github.com/eris-ltd/eris-std-lib",
	"genesis_config": "/home/zqa/go/src/github.com/eris-ltd/thelonious/monk/defaults/genesis.json",
	"log_file": "",
	"debug_file": "",
	"log_level": 2
}